{"errors":[],"warnings":[],"namedChunkGroups":{"app":{"chunks":[3,1,0],"assets":["webpack-runtime-23c0ce25fbe6cce1cdbb.js","commons-440fea4ed27491409e31.js","app-432c70cf32e3ef9890a1.js"],"children":{},"childAssets":{}},"component---src-pages-index-tsx":{"chunks":[2],"assets":["component---src-pages-index-tsx-4aa71ed5aeebd51f862e.js"],"children":{},"childAssets":{}}},"assetsByChunkName":{"app":["webpack-runtime-23c0ce25fbe6cce1cdbb.js","commons-440fea4ed27491409e31.js","app-432c70cf32e3ef9890a1.js"],"component---src-pages-index-tsx":["component---src-pages-index-tsx-4aa71ed5aeebd51f862e.js"]}}